{
  "formatVersion": 1,
  "database": {
    "version": 1,
    "identityHash": "4d8baac8b3ec8e6bbde4d79eb33fbcd9",
    "entities": [
      {
        "tableName": "storage",
        "createSql": "CREATE TABLE IF NOT EXISTS `${TABLE_NAME}` (`key` TEXT NOT NULL, `value` TEXT, PRIMARY KEY(`key`))",
        "fields": [
          {
            "fieldPath": "key",
            "columnName": "key",
            "affinity": "TEXT",
            "notNull": true
          },
          {
            "fieldPath": "value",
            "columnName": "value",
            "affinity": "TEXT"
          }
        ],
        "primaryKey": {
          "autoGenerate": false,
          "columnNames": [
            "key"
          ]
        }
      }
    ],
    "setupQueries": [
      "CREATE TABLE IF NOT EXISTS room_master_table (id INTEGER PRIMARY KEY,identity_hash TEXT)",
      "INSERT OR REPLACE INTO room_master_table (id,identity_hash) VALUES(42, '4d8baac8b3ec8e6bbde4d79eb33fbcd9')"
    ]
  }
}